README.md
setup.py
linearcli/__init__.py
linearcli/__main__.py
linearcli/linear.py
linearcli.egg-info/PKG-INFO
linearcli.egg-info/SOURCES.txt
linearcli.egg-info/dependency_links.txt
linearcli.egg-info/entry_points.txt
linearcli.egg-info/requires.txt
linearcli.egg-info/top_level.txt